backports/__init__.py
backports/functools_lru_cache.py
backports.functools_lru_cache-2.0.0.dist-info/LICENSE
backports.functools_lru_cache-2.0.0.dist-info/METADATA
backports.functools_lru_cache-2.0.0.dist-info/WHEEL
backports.functools_lru_cache-2.0.0.dist-info/top_level.txt
backports.functools_lru_cache-2.0.0.dist-info/RECORD
