Metadata-Version: 2.1
Name: backports.functools-lru-cache
Version: 2.0.0
Summary: Backport of functools.lru_cache
Home-page: https://github.com/jaraco/backports.functools_lru_cache
Author: Raymond Hettinger
Author-email: raymond.hettinger@gmail.com
Maintainer: Jason R. Coombs
Maintainer-email: jaraco@jaraco.com
Classifier: Development Status :: 5 - Production/Stable
Classifier: Intended Audience :: Developers
Classifier: License :: OSI Approved :: MIT License
Classifier: Programming Language :: Python :: 3
Requires-Python: >=3.8
License-File: LICENSE
Provides-Extra: testing
Requires-Dist: pytest>=6; extra == "testing"
Requires-Dist: pytest-checkdocs>=2.4; extra == "testing"
Requires-Dist: pytest-black>=0.3.7; platform_python_implementation != "PyPy" and extra == "testing"
Requires-Dist: pytest-cov; extra == "testing"
Requires-Dist: pytest-mypy>=0.9.1; platform_python_implementation != "PyPy" and extra == "testing"
Requires-Dist: pytest-enabler>=2.2; extra == "testing"
Requires-Dist: pytest-ruff; extra == "testing"
Provides-Extra: docs
Requires-Dist: sphinx>=3.5; extra == "docs"
Requires-Dist: sphinx<7.2.5; extra == "docs"
Requires-Dist: jaraco.packaging>=9.3; extra == "docs"
Requires-Dist: rst.linker>=1.9; extra == "docs"
Requires-Dist: furo; extra == "docs"
Requires-Dist: sphinx-lint; extra == "docs"
Requires-Dist: jaraco.tidelift>=1.4; extra == "docs"
